dev/__init__.py
dev/dev_client.py
orcatech_python_api_client/__init__.py
orcatech_python_api_client/client.py
orcatech_python_api_client/config.py
orcatech_python_api_client/exceptions.py
orcatech_python_api_client/http_client.py
orcatech_python_api_client/schema_types.py
orcatech_python_api_client/schema_types_old.py
orcatech_python_api_client/schemas.py
orcatech_python_api_client/utils.py
orcatech_python_api_client-0.1.14.dist-info/METADATA
orcatech_python_api_client-0.1.14.dist-info/WHEEL
orcatech_python_api_client-0.1.14.dist-info/entry_points.txt
orcatech_python_api_client-0.1.14.dist-info/top_level.txt
orcatech_python_api_client-0.1.14.dist-info/RECORD
