Metadata-Version: 2.1
Name: orcatech_python_api_client
Version: 0.1.14
Summary: A Python API client for Orcatech
Author: Kezman Saboi
Author-email: saboi@ohsu.edu
Classifier: Programming Language :: Python :: 3
Classifier: License :: OSI Approved :: MIT License
Classifier: Operating System :: OS Independent
Requires-Python: >=3.6
Requires-Dist: requests
Requires-Dist: python-dotenv
